{
    "new_products": [
        {
            "sku": "TU-COB-GEN-001",
            "nombre_estandarizado": "Tubo Cobre Flexible 1/4 Rollo 15.24m",
            "grupo_general": "TU",
            "grupo_especializado": "Cobre",
            "marca": "Genérico",
            "modelo": "1/4-15m",
            "descripcion_tecnica": "Rollo Tubería Cobre 1/4 15.24m",
            "capacidad": "15.24 m",
            "voltaje": "NA",
            "refrigerante": "NA",
            "tipo_operacion": "Conducción",
            "unidad": "Rollo",
            "observaciones_equivalencia": "Tubería"
        },
        {
            "sku": "TU-COB-GEN-002",
            "nombre_estandarizado": "Tubo Cobre Flexible 1/4 Tipo L Rollo 18.30m",
            "grupo_general": "TU",
            "grupo_especializado": "Cobre",
            "marca": "Genérico",
            "modelo": "1/4-L-18m",
            "descripcion_tecnica": "Rollo Tubería Cobre 1/4 Tipo L 18.30m",
            "capacidad": "18.30 m",
            "voltaje": "NA",
            "refrigerante": "NA",
            "tipo_operacion": "Conducción",
            "unidad": "Rollo",
            "observaciones_equivalencia": "Tubería"
        },
        {
            "sku": "TU-COB-GEN-003",
            "nombre_estandarizado": "Tubo Cobre Flexible 5/16 Rollo 15.24m",
            "grupo_general": "TU",
            "grupo_especializado": "Cobre",
            "marca": "Genérico",
            "modelo": "5/16-15m",
            "descripcion_tecnica": "Rollo Tubería Cobre 5/16 (8mm) 15.24m",
            "capacidad": "15.24 m",
            "voltaje": "NA",
            "refrigerante": "NA",
            "tipo_operacion": "Conducción",
            "unidad": "Rollo",
            "observaciones_equivalencia": "Tubería"
        },
        {
            "sku": "TU-COB-GEN-004",
            "nombre_estandarizado": "Tubo Cobre Flexible 1/2 Tipo L Rollo 18.30m",
            "grupo_general": "TU",
            "grupo_especializado": "Cobre",
            "marca": "Genérico",
            "modelo": "1/2-L-18m",
            "descripcion_tecnica": "Rollo Tubería Cobre 1/2 Tipo L 18.30m",
            "capacidad": "18.30 m",
            "voltaje": "NA",
            "refrigerante": "NA",
            "tipo_operacion": "Conducción",
            "unidad": "Rollo",
            "observaciones_equivalencia": "Tubería"
        },
        {
            "sku": "TU-COB-GEN-005",
            "nombre_estandarizado": "Tubo Cobre Flexible 3/4 Tipo L Rollo 18.30m",
            "grupo_general": "TU",
            "grupo_especializado": "Cobre",
            "marca": "Genérico",
            "modelo": "3/4-L-18m",
            "descripcion_tecnica": "Rollo Tubería Cobre 3/4 Tipo L 18.30m",
            "capacidad": "18.30 m",
            "voltaje": "NA",
            "refrigerante": "NA",
            "tipo_operacion": "Conducción",
            "unidad": "Rollo",
            "observaciones_equivalencia": "Tubería"
        },
        {
            "sku": "EQ-REF-CRI-009",
            "nombre_estandarizado": "Refrigerador Criotec CFX-17 Puerta Cristal",
            "grupo_general": "EQ",
            "grupo_especializado": "Refrigeradores",
            "marca": "Criotec",
            "modelo": "CFX-17",
            "descripcion_tecnica": "Refrigerador Vertical 17 ft3",
            "capacidad": "17 ft3",
            "voltaje": "115V",
            "refrigerante": "R290",
            "tipo_operacion": "Refrigeración",
            "unidad": "Pieza",
            "observaciones_equivalencia": "Equipo"
        },
        {
            "sku": "EQ-REF-CRI-010",
            "nombre_estandarizado": "Congelador Horizontal Criotec CTCC-25 Cofre",
            "grupo_general": "EQ",
            "grupo_especializado": "Refrigeradores",
            "marca": "Criotec",
            "modelo": "CTCC-25",
            "descripcion_tecnica": "Congelador Horizontal 25 ft3",
            "capacidad": "25 ft3",
            "voltaje": "115V",
            "refrigerante": "R290",
            "tipo_operacion": "Congelación",
            "unidad": "Pieza",
            "observaciones_equivalencia": "Equipo"
        },
        {
            "sku": "HE-INS-AVA-004",
            "nombre_estandarizado": "Voltamperímetro Avaly Digital 400A/600A",
            "grupo_general": "HE",
            "grupo_especializado": "Instrumentos",
            "marca": "Avaly",
            "modelo": "VA-803M",
            "descripcion_tecnica": "Multímetro Gancho Digital",
            "capacidad": "400-600A",
            "voltaje": "NA",
            "refrigerante": "NA",
            "tipo_operacion": "Medición",
            "unidad": "Pieza",
            "observaciones_equivalencia": "Instrumento"
        },
        {
            "sku": "HE-HER-BAR-003",
            "nombre_estandarizado": "Hidrolavadora Barreto 1400W",
            "grupo_general": "HE",
            "grupo_especializado": "Herramientas",
            "marca": "Barreto",
            "modelo": "HRL-1400",
            "descripcion_tecnica": "Hidrolavadora Alta Presión",
            "capacidad": "1400W",
            "voltaje": "127V",
            "refrigerante": "NA",
            "tipo_operacion": "Limpieza",
            "unidad": "Pieza",
            "observaciones_equivalencia": "Máquina"
        },
        {
            "sku": "EQ-PIT-YOR-007",
            "nombre_estandarizado": "Minisplit Piso Techo Inverter York 3 Ton 220V",
            "grupo_general": "EQ",
            "grupo_especializado": "Piso Techo",
            "marca": "York",
            "modelo": "YFJE36BZTMCMORX",
            "descripcion_tecnica": "Piso Techo Inverter Solo Frío 3 Ton",
            "capacidad": "3 Ton",
            "voltaje": "220V",
            "refrigerante": "R410A",
            "tipo_operacion": "Inverter",
            "unidad": "Pieza",
            "observaciones_equivalencia": "Equipo"
        },
        {
            "sku": "EQ-MSI-YOR-032",
            "nombre_estandarizado": "Minisplit Inverter York 1 Ton Solo Frío 110V",
            "grupo_general": "EQ",
            "grupo_especializado": "Minisplit Inverter",
            "marca": "York",
            "modelo": "YHJE12ZXMGMMORX",
            "descripcion_tecnica": "Minisplit Inverter 1 Ton 110V",
            "capacidad": "1 Ton",
            "voltaje": "110V",
            "refrigerante": "R410A",
            "tipo_operacion": "Inverter",
            "unidad": "Pieza",
            "observaciones_equivalencia": "Equipo"
        },
        {
            "sku": "EQ-MSI-LG-018",
            "nombre_estandarizado": "Minisplit Inverter LG 3 Ton Frío-Calor 220V",
            "grupo_general": "EQ",
            "grupo_especializado": "Minisplit Inverter",
            "marca": "LG",
            "modelo": "SW362H8",
            "descripcion_tecnica": "Minisplit Inverter 3 Ton F/C",
            "capacidad": "3 Ton",
            "voltaje": "220V",
            "refrigerante": "R410A",
            "tipo_operacion": "Inverter",
            "unidad": "Pieza",
            "observaciones_equivalencia": "Equipo"
        },
        {
            "sku": "AC-VEN-SOL-013",
            "nombre_estandarizado": "Extractor Helicoidal S&P 5HP 230/460V",
            "grupo_general": "AC",
            "grupo_especializado": "Ventilación",
            "marca": "Soler & Palau",
            "modelo": "HGT-1500-5",
            "descripcion_tecnica": "Extractor Helicoidal 5HP",
            "capacidad": "5 HP",
            "voltaje": "230/460V",
            "refrigerante": "NA",
            "tipo_operacion": "Ventilación",
            "unidad": "Pieza",
            "observaciones_equivalencia": "Equipo"
        },
        {
            "sku": "AC-VEN-SOL-014",
            "nombre_estandarizado": "Extractor Axial S&P HXB-400/H 1/4HP",
            "grupo_general": "AC",
            "grupo_especializado": "Ventilación",
            "marca": "Soler & Palau",
            "modelo": "HXB-400/H",
            "descripcion_tecnica": "Extractor Axial 1625 RPM",
            "capacidad": "1/4 HP",
            "voltaje": "127V",
            "refrigerante": "NA",
            "tipo_operacion": "Ventilación",
            "unidad": "Pieza",
            "observaciones_equivalencia": "Equipo"
        },
        {
            "sku": "AC-VEN-SOL-015",
            "nombre_estandarizado": "Extractor Axial S&P HXB-500/H 1/2HP",
            "grupo_general": "AC",
            "grupo_especializado": "Ventilación",
            "marca": "Soler & Palau",
            "modelo": "HXB-500/H",
            "descripcion_tecnica": "Extractor Axial 5988 CFM",
            "capacidad": "1/2 HP",
            "voltaje": "127V",
            "refrigerante": "NA",
            "tipo_operacion": "Ventilación",
            "unidad": "Pieza",
            "observaciones_equivalencia": "Equipo"
        },
        {
            "sku": "AC-VEN-SOL-016",
            "nombre_estandarizado": "Extractor Tejado S&P CRHLT-12 Descarga Horizontal",
            "grupo_general": "AC",
            "grupo_especializado": "Ventilación",
            "marca": "Soler & Palau",
            "modelo": "CRHLT-12",
            "descripcion_tecnica": "Extractor Centrifugo Tejado Horizontal",
            "capacidad": "NA",
            "voltaje": "NA",
            "refrigerante": "NA",
            "tipo_operacion": "Ventilación",
            "unidad": "Pieza",
            "observaciones_equivalencia": "Equipo"
        },
        {
            "sku": "AC-VEN-SOL-017",
            "nombre_estandarizado": "Cortina de Aire S&P CES-48 48 Pulgadas",
            "grupo_general": "AC",
            "grupo_especializado": "Ventilación",
            "marca": "Soler & Palau",
            "modelo": "CES-48",
            "descripcion_tecnica": "Cortina Aire 48 Pulgadas",
            "capacidad": "48 in",
            "voltaje": "127V",
            "refrigerante": "NA",
            "tipo_operacion": "Ventilación",
            "unidad": "Pieza",
            "observaciones_equivalencia": "Equipo"
        },
        {
            "sku": "AC-VEN-SOL-018",
            "nombre_estandarizado": "Extractor Baño S&P Decor Design 300",
            "grupo_general": "AC",
            "grupo_especializado": "Ventilación",
            "marca": "Soler & Palau",
            "modelo": "Decor Design 300",
            "descripcion_tecnica": "Extractor Baño 1750 RPM",
            "capacidad": "NA",
            "voltaje": "NA",
            "refrigerante": "NA",
            "tipo_operacion": "Ventilación",
            "unidad": "Pieza",
            "observaciones_equivalencia": "Equipo"
        },
        {
            "sku": "AC-VEN-SOL-019",
            "nombre_estandarizado": "Persiana Plástico S&P 4 Pulgadas",
            "grupo_general": "AC",
            "grupo_especializado": "Ventilación",
            "marca": "Soler & Palau",
            "modelo": "PER-301",
            "descripcion_tecnica": "Persiana Plástico 3 Aletas",
            "capacidad": "4 in",
            "voltaje": "NA",
            "refrigerante": "NA",
            "tipo_operacion": "Ventilación",
            "unidad": "Pieza",
            "observaciones_equivalencia": "Accesorio"
        },
        {
            "sku": "AC-VEN-SOL-020",
            "nombre_estandarizado": "Extractor Helicoidal S&P 3HP 610RPM",
            "grupo_general": "AC",
            "grupo_especializado": "Ventilación",
            "marca": "Soler & Palau",
            "modelo": "HGT-1250-3",
            "descripcion_tecnica": "Extractor Helicoidal 3HP",
            "capacidad": "3 HP",
            "voltaje": "NA",
            "refrigerante": "NA",
            "tipo_operacion": "Ventilación",
            "unidad": "Pieza",
            "observaciones_equivalencia": "Equipo"
        },
        {
            "sku": "AC-VEN-SOL-021",
            "nombre_estandarizado": "Extractor Pared S&P HCM-180",
            "grupo_general": "AC",
            "grupo_especializado": "Ventilación",
            "marca": "Soler & Palau",
            "modelo": "HCM-180",
            "descripcion_tecnica": "Extractor Pared/Ventana 500m3/hr",
            "capacidad": "NA",
            "voltaje": "NA",
            "refrigerante": "NA",
            "tipo_operacion": "Ventilación",
            "unidad": "Pieza",
            "observaciones_equivalencia": "Equipo"
        },
        {
            "sku": "AC-VEN-SOL-022",
            "nombre_estandarizado": "Extractor Tejado S&P CRHLT-18",
            "grupo_general": "AC",
            "grupo_especializado": "Ventilación",
            "marca": "Soler & Palau",
            "modelo": "CRHLT-18",
            "descripcion_tecnica": "Extractor Centrifugo Tejado",
            "capacidad": "NA",
            "voltaje": "NA",
            "refrigerante": "NA",
            "tipo_operacion": "Ventilación",
            "unidad": "Pieza",
            "observaciones_equivalencia": "Equipo"
        },
        {
            "sku": "AC-VEN-SOL-023",
            "nombre_estandarizado": "Extractor Tejado S&P CRHLT-14 Descarga Horizontal",
            "grupo_general": "AC",
            "grupo_especializado": "Ventilación",
            "marca": "Soler & Palau",
            "modelo": "CRHLT-14",
            "descripcion_tecnica": "Extractor Centrifugo Tejado Horizontal",
            "capacidad": "NA",
            "voltaje": "NA",
            "refrigerante": "NA",
            "tipo_operacion": "Ventilación",
            "unidad": "Pieza",
            "observaciones_equivalencia": "Equipo"
        },
        {
            "sku": "AC-VEN-SOL-024",
            "nombre_estandarizado": "Cortina de Aire S&P CAS-36 36 Pulgadas",
            "grupo_general": "AC",
            "grupo_especializado": "Ventilación",
            "marca": "Soler & Palau",
            "modelo": "CAS-36",
            "descripcion_tecnica": "Cortina Aire 36 Pulgadas",
            "capacidad": "36 in",
            "voltaje": "127V",
            "refrigerante": "NA",
            "tipo_operacion": "Ventilación",
            "unidad": "Pieza",
            "observaciones_equivalencia": "Equipo"
        },
        {
            "sku": "AC-VEN-SOL-025",
            "nombre_estandarizado": "Extractor Ducto S&P TD-350/125",
            "grupo_general": "AC",
            "grupo_especializado": "Ventilación",
            "marca": "Soler & Palau",
            "modelo": "TD-350/125",
            "descripcion_tecnica": "Extractor Helicocentrífugo Ducto",
            "capacidad": "NA",
            "voltaje": "127V",
            "refrigerante": "NA",
            "tipo_operacion": "Ventilación",
            "unidad": "Pieza",
            "observaciones_equivalencia": "Equipo"
        },
        {
            "sku": "AC-VEN-AVA-002",
            "nombre_estandarizado": "Extractor Aire 4 Pulgadas Avaly",
            "grupo_general": "AC",
            "grupo_especializado": "Ventilación",
            "marca": "Avaly",
            "modelo": "VA-100E",
            "descripcion_tecnica": "Extractor Aire 4\"",
            "capacidad": "4 in",
            "voltaje": "NA",
            "refrigerante": "NA",
            "tipo_operacion": "Ventilación",
            "unidad": "Pieza",
            "observaciones_equivalencia": "Equipo"
        },
        {
            "sku": "AC-VEN-SOL-026",
            "nombre_estandarizado": "Extractor Baño S&P Future 100",
            "grupo_general": "AC",
            "grupo_especializado": "Ventilación",
            "marca": "Soler & Palau",
            "modelo": "FUTURE-100",
            "descripcion_tecnica": "Extractor Baño Habitat Future",
            "capacidad": "56 CFM",
            "voltaje": "127V",
            "refrigerante": "NA",
            "tipo_operacion": "Ventilación",
            "unidad": "Pieza",
            "observaciones_equivalencia": "Equipo"
        },
        {
            "sku": "EQ-MSI-HIS-019",
            "nombre_estandarizado": "Minisplit Inverter Hisense WiFi 1.5 Ton Solo Frío 220V",
            "grupo_general": "EQ",
            "grupo_especializado": "Minisplit Inverter",
            "marca": "Hisense",
            "modelo": "ART182KAW",
            "descripcion_tecnica": "Minisplit Inverter 1.5 Ton WiFi",
            "capacidad": "1.5 Ton",
            "voltaje": "220V",
            "refrigerante": "NA",
            "tipo_operacion": "Inverter",
            "unidad": "Pieza",
            "observaciones_equivalencia": "Equipo"
        },
        {
            "sku": "EQ-MSO-15T220-011",
            "nombre_estandarizado": "Minisplit On/Off Prime Elite 1.5 Ton Solo Frío 220V",
            "grupo_general": "EQ",
            "grupo_especializado": "Minisplit On/Off",
            "marca": "Prime",
            "modelo": "EMPRC182-E2",
            "descripcion_tecnica": "Minisplit Elite 1.5 Ton Solo Frío",
            "capacidad": "1.5 Ton",
            "voltaje": "220V",
            "refrigerante": "R410A",
            "tipo_operacion": "On/Off",
            "unidad": "Pieza",
            "observaciones_equivalencia": "Equipo"
        },
        {
            "sku": "EQ-MSI-PRI-023",
            "nombre_estandarizado": "Minisplit Inverter Prime Brgt 1.5 Ton Solo Frío 220V",
            "grupo_general": "EQ",
            "grupo_especializado": "Minisplit Inverter",
            "marca": "Prime",
            "modelo": "EMPRC182-B",
            "descripcion_tecnica": "Minisplit Brgt Inverter 1.5 Ton",
            "capacidad": "1.5 Ton",
            "voltaje": "220V",
            "refrigerante": "R410A",
            "tipo_operacion": "Inverter",
            "unidad": "Pieza",
            "observaciones_equivalencia": "Equipo"
        },
        {
            "sku": "EQ-MSO-2T220-010",
            "nombre_estandarizado": "Minisplit On/Off Prime Trendy 2 Ton Frío-Calor 220V",
            "grupo_general": "EQ",
            "grupo_especializado": "Minisplit On/Off",
            "marca": "Prime",
            "modelo": "EMPRN242-T3",
            "descripcion_tecnica": "Minisplit Trendy 2 Ton F/C",
            "capacidad": "2 Ton",
            "voltaje": "220V",
            "refrigerante": "NA",
            "tipo_operacion": "On/Off",
            "unidad": "Pieza",
            "observaciones_equivalencia": "Equipo"
        },
        {
            "sku": "AC-BOM-ASP-004",
            "nombre_estandarizado": "Bomba Condensado Aspen Mini White Univolt",
            "grupo_general": "AC",
            "grupo_especializado": "Bombas",
            "marca": "Aspen",
            "modelo": "FP1058",
            "descripcion_tecnica": "Bomba Condensado 100-250V",
            "capacidad": "NA",
            "voltaje": "100-250V",
            "refrigerante": "NA",
            "tipo_operacion": "Bombeo",
            "unidad": "Pieza",
            "observaciones_equivalencia": "Accesorio"
        },
        {
            "sku": "AC-VEN-SOL-027",
            "nombre_estandarizado": "Extractor Axial Pared S&P HXM-200",
            "grupo_general": "AC",
            "grupo_especializado": "Ventilación",
            "marca": "Soler & Palau",
            "modelo": "HXM-200",
            "descripcion_tecnica": "Extractor Axial 388 CFM",
            "capacidad": "NA",
            "voltaje": "127V",
            "refrigerante": "NA",
            "tipo_operacion": "Ventilación",
            "unidad": "Pieza",
            "observaciones_equivalencia": "Equipo"
        },
        {
            "sku": "EQ-VIT-CRI-002",
            "nombre_estandarizado": "Vitrina Curva Criotec VCC-200 31.9 ft3",
            "grupo_general": "EQ",
            "grupo_especializado": "Refrigeradores",
            "marca": "Criotec",
            "modelo": "VCC-200",
            "descripcion_tecnica": "Vitrina Curva 31.9 Pies",
            "capacidad": "31.9 ft3",
            "voltaje": "NA",
            "refrigerante": "NA",
            "tipo_operacion": "Refrigeración",
            "unidad": "Pieza",
            "observaciones_equivalencia": "Equipo"
        },
        {
            "sku": "EQ-MSO-1T220-013",
            "nombre_estandarizado": "Minisplit On/Off York High Wall 1 Ton Solo Frío 220V",
            "grupo_general": "EQ",
            "grupo_especializado": "Minisplit On/Off",
            "marca": "York",
            "modelo": "YHFE12ZJMAXAORX",
            "descripcion_tecnica": "Minisplit High Wall 1 Ton R410A",
            "capacidad": "1 Ton",
            "voltaje": "220V",
            "refrigerante": "R410A",
            "tipo_operacion": "On/Off",
            "unidad": "Pieza",
            "observaciones_equivalencia": "Equipo"
        },
        {
            "sku": "EQ-MSO-1T110-008",
            "nombre_estandarizado": "Minisplit On/Off Midea 1 Ton Solo Frío 110V",
            "grupo_general": "EQ",
            "grupo_especializado": "Minisplit On/Off",
            "marca": "Midea",
            "modelo": "MAS12C1AGO",
            "descripcion_tecnica": "Minisplit Estándar 1 Ton 110V",
            "capacidad": "1 Ton",
            "voltaje": "110V",
            "refrigerante": "NA",
            "tipo_operacion": "On/Off",
            "unidad": "Pieza",
            "observaciones_equivalencia": "Equipo"
        },
        {
            "sku": "EQ-MSO-1T220-014",
            "nombre_estandarizado": "Minisplit On/Off Hisense 1 Ton Solo Frío 220V",
            "grupo_general": "EQ",
            "grupo_especializado": "Minisplit On/Off",
            "marca": "Hisense",
            "modelo": "AC122CK",
            "descripcion_tecnica": "Minisplit Estándar 1 Ton 220V",
            "capacidad": "1 Ton",
            "voltaje": "220V",
            "refrigerante": "NA",
            "tipo_operacion": "On/Off",
            "unidad": "Pieza",
            "observaciones_equivalencia": "Equipo"
        },
        {
            "sku": "EQ-MSO-1T220-015",
            "nombre_estandarizado": "Minisplit On/Off Samsung 1 Ton Solo Frío 220V",
            "grupo_general": "EQ",
            "grupo_especializado": "Minisplit On/Off",
            "marca": "Samsung",
            "modelo": "AR12TRHQEWK/AX",
            "descripcion_tecnica": "Minisplit Estándar 1 Ton 220V",
            "capacidad": "1 Ton",
            "voltaje": "220V",
            "refrigerante": "R410A",
            "tipo_operacion": "On/Off",
            "unidad": "Pieza",
            "observaciones_equivalencia": "Equipo"
        },
        {
            "sku": "EQ-MSO-1T220-016",
            "nombre_estandarizado": "Minisplit On/Off TCL 1 Ton Solo Frío 220V",
            "grupo_general": "EQ",
            "grupo_especializado": "Minisplit On/Off",
            "marca": "TCL",
            "modelo": "S12P-ECF22",
            "descripcion_tecnica": "Minisplit Estándar 1 Ton 220V",
            "capacidad": "1 Ton",
            "voltaje": "220V",
            "refrigerante": "R410A",
            "tipo_operacion": "On/Off",
            "unidad": "Pieza",
            "observaciones_equivalencia": "Equipo"
        }
    ],
    "price_observations": [
        {
            "sku": "TU-COB-GEN-001",
            "precio": "1125.0",
            "proveedor": "Plomería Universal",
            "sku_original": "6100",
            "url": "https://plomeriauniversal.mx/products/tubo-cobre-flexible?variant=39637645787288",
            "scraped_at": "2025-12-26 19:52:03",
            "raw_id": "3242"
        },
        {
            "sku": "TU-COB-GEN-002",
            "precio": "1675.5",
            "proveedor": "Plomería Universal",
            "sku_original": "6093",
            "url": "https://plomeriauniversal.mx/products/tubo-cobre-flexible?variant=39637645885592",
            "scraped_at": "2025-12-26 19:52:03",
            "raw_id": "3244"
        },
        {
            "sku": "TU-COB-GEN-003",
            "precio": "1278.75",
            "proveedor": "Plomería Universal",
            "sku_original": "6102",
            "url": "https://plomeriauniversal.mx/products/tubo-cobre-flexible?variant=40204748030104",
            "scraped_at": "2025-12-26 19:52:03",
            "raw_id": "3246"
        },
        {
            "sku": "TU-COB-GEN-004",
            "precio": "2998.5",
            "proveedor": "Plomería Universal",
            "sku_original": "6096",
            "url": "https://plomeriauniversal.mx/products/tubo-cobre-flexible?variant=39637646082200",
            "scraped_at": "2025-12-26 19:52:03",
            "raw_id": "3248"
        },
        {
            "sku": "TU-COB-GEN-005",
            "precio": "4852.5",
            "proveedor": "Plomería Universal",
            "sku_original": "6097",
            "url": "https://plomeriauniversal.mx/products/tubo-cobre-flexible?variant=40204747440280",
            "scraped_at": "2025-12-26 19:52:03",
            "raw_id": "3250"
        },
        {
            "sku": "EQ-REF-CRI-009",
            "precio": "25901.16",
            "proveedor": "Reacsa",
            "sku_original": "CFX-17",
            "url": "https://reacsa.mx/products/refrigerador-criotec-cfx-17-puerta-de-cristal",
            "scraped_at": "2025-12-26 19:52:36",
            "raw_id": "3255"
        },
        {
            "sku": "EQ-REF-CRI-010",
            "precio": "25375.24",
            "proveedor": "Reacsa",
            "sku_original": "CTCC-25",
            "url": "https://reacsa.mx/products/ctcc-25-congelador-horizontal-25-puerta-solida-tapa-cofre",
            "scraped_at": "2025-12-26 19:52:36",
            "raw_id": "3256"
        },
        {
            "sku": "HE-INS-AVA-004",
            "precio": "808.42",
            "proveedor": "Reacsa",
            "sku_original": "VA-803M#",
            "url": "https://reacsa.mx/products/voltamperimetro-avaly-digital-400a-600a",
            "scraped_at": "2025-12-26 19:52:36",
            "raw_id": "3257"
        },
        {
            "sku": "HE-HER-BAR-003",
            "precio": "2214.35",
            "proveedor": "Reacsa",
            "sku_original": "HRL-1400",
            "url": "NA",
            "scraped_at": "2025-12-26 19:52:36",
            "raw_id": "3273"
        },
        {
            "sku": "EQ-PIT-YOR-007",
            "precio": "28803.0",
            "proveedor": "Reacsa",
            "sku_original": "YFJE36BZTMCMORX",
            "url": "https://reacsa.mx/products/minisplit-york-piso-techo-inverter-solo-frio-3-ton-220v-r410a",
            "scraped_at": "2025-12-26 19:52:36",
            "raw_id": "3278"
        },
        {
            "sku": "EQ-MSI-YOR-032",
            "precio": "7323.46",
            "proveedor": "Reacsa",
            "sku_original": "YHJE12ZXMGMMORX",
            "url": "https://reacsa.mx/products/minisplit-york-1-ton-solo-frio-inverter-110v",
            "scraped_at": "2025-12-26 19:52:36",
            "raw_id": "3288"
        },
        {
            "sku": "EQ-MSI-LG-018",
            "precio": "37619.08",
            "proveedor": "Reacsa",
            "sku_original": "SW362H8",
            "url": "https://reacsa.mx/products/minisplit-lg-inverter-frio-calor-3-ton-110-v-220-1-r410",
            "scraped_at": "2025-12-26 19:52:36",
            "raw_id": "3299"
        },
        {
            "sku": "AC-VEN-SOL-013",
            "precio": "77072.22",
            "proveedor": "Reacsa",
            "sku_original": "HGT-1500-5",
            "url": "https://reacsa.mx/products/extractor-s-p-helicoidal-5hp-230-460",
            "scraped_at": "2025-12-26 19:52:36",
            "raw_id": "3310"
        },
        {
            "sku": "AC-VEN-SOL-014",
            "precio": "8820.76",
            "proveedor": "Reacsa",
            "sku_original": "HXB-400/H",
            "url": "https://reacsa.mx/products/extractor-s-p-axial-hxb-500-h-1-2-hp-127v-5-988-cfm-s-copy",
            "scraped_at": "2025-12-26 19:52:36",
            "raw_id": "3311"
        },
        {
            "sku": "AC-VEN-SOL-015",
            "precio": "12981.91",
            "proveedor": "Reacsa",
            "sku_original": "HXB-500/H",
            "url": "https://reacsa.mx/products/extractor-s-p-axial-hxb-500-h-1-2-hp-127v-5-988-cfm-s",
            "scraped_at": "2025-12-26 19:52:36",
            "raw_id": "3312"
        },
        {
            "sku": "AC-VEN-SOL-016",
            "precio": "21243.97",
            "proveedor": "Reacsa",
            "sku_original": "CRHLT-12 S/M",
            "url": "https://reacsa.mx/products/crhlt-12-s-m-extractor-centrifugador-tejado-5crhlt120000000-d-horiz",
            "scraped_at": "2025-12-26 19:52:36",
            "raw_id": "3313"
        },
        {
            "sku": "AC-VEN-SOL-017",
            "precio": "6936.9",
            "proveedor": "Reacsa",
            "sku_original": "5CES-48",
            "url": "https://reacsa.mx/products/cortina-de-aire-48-ces-s-p-1582rpm-208w-127v",
            "scraped_at": "2025-12-26 19:52:36",
            "raw_id": "3314"
        },
        {
            "sku": "AC-VEN-SOL-018",
            "precio": "3906.71",
            "proveedor": "Reacsa",
            "sku_original": "5DECOR-300",
            "url": "https://reacsa.mx/products/extractor-s-p-para-bano-decor-design-300-1750rpm",
            "scraped_at": "2025-12-26 19:52:36",
            "raw_id": "3315"
        },
        {
            "sku": "AC-VEN-SOL-019",
            "precio": "185.7",
            "proveedor": "Reacsa",
            "sku_original": "5PER-301",
            "url": "https://reacsa.mx/products/persiana-s-p-plastico-4-3-aletas",
            "scraped_at": "2025-12-26 19:52:36",
            "raw_id": "3316"
        },
        {
            "sku": "AC-VEN-SOL-020",
            "precio": "48575.82",
            "proveedor": "Reacsa",
            "sku_original": "HGT-1250-3",
            "url": "https://reacsa.mx/products/extractor-s-p-helicoidal-3hp-610rpm",
            "scraped_at": "2025-12-26 19:52:36",
            "raw_id": "3317"
        },
        {
            "sku": "AC-VEN-SOL-021",
            "precio": "2642.12",
            "proveedor": "Reacsa",
            "sku_original": "HCM-180",
            "url": "https://reacsa.mx/products/extractor-pra-pared-y-ventana-s-p-500m3-hr",
            "scraped_at": "2025-12-26 19:52:36",
            "raw_id": "3318"
        },
        {
            "sku": "AC-VEN-SOL-022",
            "precio": "29747.5",
            "proveedor": "Reacsa",
            "sku_original": "CRHLT-18 S/M",
            "url": "https://reacsa.mx/products/crhlt-18-s-m-extractor-centrifugador-tejado-5crhlt180000000",
            "scraped_at": "2025-12-26 19:52:36",
            "raw_id": "3319"
        },
        {
            "sku": "AC-VEN-SOL-023",
            "precio": "25166.22",
            "proveedor": "Reacsa",
            "sku_original": "CRHLT-14 S/M",
            "url": "https://reacsa.mx/products/crhlt-14-s-m-extractor-centrifugado-tejado-5crhlt140000000-d-horiz",
            "scraped_at": "2025-12-26 19:52:36",
            "raw_id": "3320"
        },
        {
            "sku": "AC-VEN-SOL-024",
            "precio": "6255.93",
            "proveedor": "Reacsa",
            "sku_original": "CAS-36",
            "url": "https://reacsa.mx/products/cas-series-cortinas-aire-s-p-de-36-48-y-60-pulgadas-130-188w-127",
            "scraped_at": "2025-12-26 19:52:36",
            "raw_id": "3321"
        },
        {
            "sku": "AC-VEN-SOL-025",
            "precio": "5411.5",
            "proveedor": "Reacsa",
            "sku_original": "TD-350/125",
            "url": "https://reacsa.mx/products/extractor-de-aire-para-ducto-s-p-helico-centrifugo-127v-5td-350",
            "scraped_at": "2025-12-26 19:52:36",
            "raw_id": "3322"
        },
        {
            "sku": "AC-VEN-AVA-002",
            "precio": "356.7",
            "proveedor": "Reacsa",
            "sku_original": "VA-100E",
            "url": "https://reacsa.mx/products/extractor-de-aire-de-4-avaly",
            "scraped_at": "2025-12-26 19:52:36",
            "raw_id": "3323"
        },
        {
            "sku": "AC-VEN-SOL-026",
            "precio": "1066.53",
            "proveedor": "Reacsa",
            "sku_original": "FUTURE-100",
            "url": "https://reacsa.mx/products/future-100-extractor-s-p-habitat-future-56cfm-13w-127v",
            "scraped_at": "2025-12-26 19:52:36",
            "raw_id": "3324"
        },
        {
            "sku": "EQ-MSI-HIS-019",
            "precio": "9969.74",
            "proveedor": "Reacsa",
            "sku_original": "ART182KAW",
            "url": "https://reacsa.mx/products/minisplit-hisense-wifi-1-5-tonelada-solo-frio-inverter-220v",
            "scraped_at": "2025-12-26 19:52:36",
            "raw_id": "3325"
        },
        {
            "sku": "EQ-MSO-15T220-011",
            "precio": "8406.37",
            "proveedor": "Reacsa",
            "sku_original": "EMPRC182-E2",
            "url": "https://reacsa.mx/products/minisplit-prime-elite-1-5ton-solo-frio-estandar-220v",
            "scraped_at": "2025-12-26 19:52:36",
            "raw_id": "3326"
        },
        {
            "sku": "EQ-MSI-PRI-023",
            "precio": "9628.37",
            "proveedor": "Reacsa",
            "sku_original": "EMPRC182-B",
            "url": "https://reacsa.mx/products/minisplit-prime-brgt-1-5ton-solo-frio-inverter-220v",
            "scraped_at": "2025-12-26 19:52:36",
            "raw_id": "3327"
        },
        {
            "sku": "EQ-MSO-2T220-010",
            "precio": "11837.64",
            "proveedor": "Reacsa",
            "sku_original": "EMPRN242-T3",
            "url": "https://reacsa.mx/products/minisplit-prime-trendy-2t-frio-y-calor-estandar-220v",
            "scraped_at": "2025-12-26 19:52:36",
            "raw_id": "3328"
        },
        {
            "sku": "AC-BOM-ASP-004",
            "precio": "2271.43",
            "proveedor": "Reacsa",
            "sku_original": "FP1058",
            "url": "https://reacsa.mx/products/bomba-aspen-mini-white-univolt-100-250v",
            "scraped_at": "2025-12-26 19:52:36",
            "raw_id": "3329"
        },
        {
            "sku": "AC-VEN-SOL-027",
            "precio": "2493.04",
            "proveedor": "Reacsa",
            "sku_original": "HXM-200",
            "url": "https://reacsa.mx/products/extractor-axial-de-pared-s-p-1-70hp500",
            "scraped_at": "2025-12-26 19:52:36",
            "raw_id": "3330"
        },
        {
            "sku": "EQ-VIT-CRI-002",
            "precio": "62694.14",
            "proveedor": "Reacsa",
            "sku_original": "VCC-200",
            "url": "https://reacsa.mx/products/vcc-200-vitrina-curva-criotec-de-31-9-pies",
            "scraped_at": "2025-12-26 19:52:36",
            "raw_id": "3331"
        },
        {
            "sku": "EQ-MSO-1T220-013",
            "precio": "6032.77",
            "proveedor": "Reacsa",
            "sku_original": "YHFE12ZJMAXAORX",
            "url": "https://reacsa.mx/products/york-minisplit-compresor-on-off-solo-frio-1-ton-220v-r-410a",
            "scraped_at": "2025-12-26 19:52:36",
            "raw_id": "3332"
        },
        {
            "sku": "EQ-MSO-1T110-008",
            "precio": "6573.49",
            "proveedor": "Reacsa",
            "sku_original": "MAS12C1AGO",
            "url": "https://reacsa.mx/products/minisplit-midea-estandar-1-ton-solo-frio-110v",
            "scraped_at": "2025-12-26 19:52:36",
            "raw_id": "3333"
        },
        {
            "sku": "EQ-MSO-1T220-014",
            "precio": "5115.26",
            "proveedor": "Reacsa",
            "sku_original": "AC122CK",
            "url": "https://reacsa.mx/products/minisplit-hisense-1-ton-solo-frio-estandar-220v",
            "scraped_at": "2025-12-26 19:52:36",
            "raw_id": "3334"
        },
        {
            "sku": "EQ-MSO-1T220-015",
            "precio": "6550.98",
            "proveedor": "Reacsa",
            "sku_original": "AR12TRHQEWK/AX",
            "url": "https://reacsa.mx/products/essential-series-minisplit-samsung-solo-frio-220-1-on-off",
            "scraped_at": "2025-12-26 19:52:36",
            "raw_id": "3335"
        },
        {
            "sku": "EQ-MSO-1T220-016",
            "precio": "5384.44",
            "proveedor": "Reacsa",
            "sku_original": "S12P-ECF22",
            "url": "https://reacsa.mx/products/minisplit-tcl-1-ton-solo-frio-estandar-r410a-220v",
            "scraped_at": "2025-12-26 19:52:36",
            "raw_id": "3336"
        }
    ]
}